favapy/__init__.py
favapy/fava.py
favapy-1.0.1.dist-info/LICENSE
favapy-1.0.1.dist-info/METADATA
favapy-1.0.1.dist-info/WHEEL
favapy-1.0.1.dist-info/entry_points.txt
favapy-1.0.1.dist-info/top_level.txt
favapy-1.0.1.dist-info/RECORD
