Metadata-Version: 2.1
Name: favapy
Version: 1.0.1
Summary: Infer Functional Associations using Variational Autoencoders on -Omics data.
Home-page: https://github.com/mikelkou/VAE_Functional_associations
Author: Mikaela Koutrouli
Author-email: mikaela.koutrouli@cpr.ku.dk
Project-URL: Bug Tracker, https://github.com/mikelkou/VAE_Functional_associations/issues
Classifier: Programming Language :: Python :: 3
Classifier: License :: OSI Approved :: MIT License
Classifier: Operating System :: OS Independent
Classifier: Intended Audience :: Science/Research
Classifier: Topic :: Scientific/Engineering :: Bio-Informatics
Requires-Python: >=3.7
License-File: LICENSE
Requires-Dist: tensorflow
Requires-Dist: keras
Requires-Dist: numpy
Requires-Dist: pandas
Requires-Dist: anndata
Provides-Extra: docs
Requires-Dist: nbsphinx ; extra == 'docs'
Provides-Extra: test
Requires-Dist: pytest ; extra == 'test'
Requires-Dist: pytest-cov ; extra == 'test'
